LICENSE
MANIFEST.in
Makefile
README.rst
httpauth.py
setup.py
test_httpauth.py
httpauth.egg-info/PKG-INFO
httpauth.egg-info/SOURCES.txt
httpauth.egg-info/dependency_links.txt
httpauth.egg-info/top_level.txt